dataportal.py
dataportal-0.0.6.dist-info/METADATA
dataportal-0.0.6.dist-info/WHEEL
dataportal-0.0.6.dist-info/top_level.txt
dataportal-0.0.6.dist-info/RECORD
