Metadata-Version: 2.1
Name: dataportal
Version: 0.0.6
Summary: 공공데이터포털 api 다운로드
Home-page: https://github.com/theB10ssom/DataPortal
Author: Yongmin
Author-email: jhk3211@icloud.com
License: MIT
Platform: UNKNOWN
Classifier: Programming Language :: Python :: 3
Classifier: License :: OSI Approved :: MIT License
Classifier: Operating System :: OS Independent
Requires-Dist: xmltodict (>=0.12.0)
Requires-Dist: requests (>=2.25.1)
Requires-Dist: urllib3 (>=1.26.4)
